{
  "deps": [
    ":snapshot:clock",
    ":snapshot:identity"
  ],
  "entry": false,
  "interface": "src/api.rs",
  "packages": [
    { "name": "rusqlite", "version": "0.31" }
  ],
  "reqs": [
    "013.1",
    "013.2",
    "013.3",
    "013.4",
    "013.5",
    "013.6",
    "013.7",
    "013.8",
    "013.9",
    "013.10",
    "013.11",
    "013.12",
    "013.13",
    "013.14",
    "013.15",
    "013.16",
    "013.17",
    "013.18",
    "013.19",
    "013.20",
    "017.1",
    "017.2",
    "017.3",
    "017.4",
    "017.5",
    "017.6",
    "017.7",
    "017.8",
    "017.9",
    "017.10",
    "017.11",
    "017.12",
    "017.13",
    "017.14",
    "017.15",
    "017.16",
    "017.17",
    "017.18",
    "017.19",
    "017.20",
    "017.21",
    "017.22",
    "018.1",
    "018.2",
    "018.3",
    "018.4",
    "018.5",
    "018.6",
    "024.6"
  ],
  "shared": false,
  "wiring": "per-dependent"
}
